gigs_client/__init__.py
gigs_client/api/__init__.py
gigs_client/api/addons_api.py
gigs_client/api/devices_api.py
gigs_client/api/plans_api.py
gigs_client/api/portings_api.py
gigs_client/api/projects_api.py
gigs_client/api/sims_api.py
gigs_client/api/subscription_addons_api.py
gigs_client/api/subscription_changes_api.py
gigs_client/api/subscriptions_api.py
gigs_client/api/usage_api.py
gigs_client/api/user_addresses_api.py
gigs_client/api/users_api.py
gigs_client/api_client.py
gigs_client/api_response.py
gigs_client/configuration.py
gigs_client/exceptions.py
gigs_client/models/__init__.py
gigs_client/models/addon.py
gigs_client/models/addon_price.py
gigs_client/models/addon_validity.py
gigs_client/models/addons_list200_response.py
gigs_client/models/addons_update_request.py
gigs_client/models/coverage.py
gigs_client/models/device.py
gigs_client/models/device_model.py
gigs_client/models/device_model_brands.py
gigs_client/models/device_models_search200_response.py
gigs_client/models/device_models_search_request.py
gigs_client/models/device_user.py
gigs_client/models/devices_create_request.py
gigs_client/models/devices_search200_response.py
gigs_client/models/devices_search_request.py
gigs_client/models/devices_update_request.py
gigs_client/models/error.py
gigs_client/models/organization.py
gigs_client/models/period.py
gigs_client/models/plan.py
gigs_client/models/plan_document.py
gigs_client/models/plan_documents_list200_response.py
gigs_client/models/plan_requirements.py
gigs_client/models/plans_search200_response.py
gigs_client/models/plans_search_request.py
gigs_client/models/plans_search_request_compatible_with.py
gigs_client/models/plans_update_request.py
gigs_client/models/porting.py
gigs_client/models/porting_donor_provider.py
gigs_client/models/porting_recipient_provider.py
gigs_client/models/portings_create_request.py
gigs_client/models/portings_list200_response.py
gigs_client/models/portings_update_request.py
gigs_client/models/price.py
gigs_client-0.0.1.dist-info/METADATA
gigs_client-0.0.1.dist-info/WHEEL
gigs_client-0.0.1.dist-info/RECORD
